LICENSE.txt
MANIFEST.in
README.rst
readme.rst
requirements.txt
setup.cfg
setup.py
geomate/__init__.py
geomate/batch.py
geomate/logger.py
geomate/zzz_manual_install.py
geomate.egg-info/PKG-INFO
geomate.egg-info/SOURCES.txt
geomate.egg-info/dependency_links.txt
geomate.egg-info/requires.txt
geomate.egg-info/top_level.txt
geomate/geocoderAPI/__init__.py
geomate/geocoderAPI/base.py
geomate/geocoderAPI/google.py