Metadata-Version: 1.1
Name: geomate
Version: 0.0.7
Summary: geomate is a automate geocoding tools using Google GeoCoding API.
Home-page: https://github.com/MacHu-GWU/geomate-project
Author: Sanhe Hu
Author-email: husanhe@gmail.com
License: MIT
Download-URL: https://github.com/MacHu-GWU/geomate-project/tarball/2016-01-22
Platform: Windows
Platform: MacOS
Platform: Unix
Classifier: Development Status :: 4 - Beta
Classifier: Intended Audience :: Developers
Classifier: License :: OSI Approved :: MIT License
Classifier: Natural Language :: English
Classifier: Operating System :: Microsoft :: Windows
Classifier: Operating System :: MacOS
Classifier: Operating System :: Unix
Classifier: Programming Language :: Python
Classifier: Programming Language :: Python :: 2
Classifier: Programming Language :: Python :: 2.7
Classifier: Programming Language :: Python :: 3
Classifier: Programming Language :: Python :: 3.3
Classifier: Programming Language :: Python :: 3.4
